rda_python_dsquasar/__init__.py
rda_python_dsquasar/ds_quasar.py
rda_python_dsquasar/dsquasar.py
rda_python_dsquasar-2.0.2.dist-info/licenses/LICENSE
rda_python_dsquasar-2.0.2.dist-info/METADATA
rda_python_dsquasar-2.0.2.dist-info/WHEEL
rda_python_dsquasar-2.0.2.dist-info/entry_points.txt
rda_python_dsquasar-2.0.2.dist-info/top_level.txt
rda_python_dsquasar-2.0.2.dist-info/RECORD
