Metadata-Version: 2.4
Name: rda_python_dsquasar
Version: 2.0.2
Summary: RDA Python package to backup and recover RDA data archives to and from GLOBUS Quasar backup server
Author-email: Zaihua Ji <zji@ucar.edu>
Project-URL: Homepage, https://github.com/NCAR/rda-python-dsquasar
Classifier: Programming Language :: Python :: 3
Classifier: License :: OSI Approved :: MIT License
Classifier: Operating System :: OS Independent
Classifier: Development Status :: 5 - Production/Stable
Requires-Python: >=3.7
License-File: LICENSE
Requires-Dist: rda_python_common
Requires-Dist: rda_python_dsarch
Dynamic: license-file
